{
  "incumbent_ids": [
    49
  ],
  "rejected_config_ids": [
    2,
    3,
    4,
    5,
    6,
    7,
    8,
    9,
    10,
    11,
    12,
    1,
    14,
    13,
    16,
    17,
    18,
    15,
    20,
    19,
    22,
    21,
    24,
    23,
    25,
    27,
    28,
    29,
    30,
    31,
    32,
    33,
    34,
    35,
    36,
    37,
    38,
    39,
    40,
    41,
    42,
    43,
    44,
    45,
    46,
    26,
    48,
    47,
    50
  ],
  "incumbents_changed": 10,
  "trajectory": [
    {
      "config_ids": [
        1
      ],
      "costs": [
        -141.24464416503906
      ],
      "trial": 1,
      "walltime": 0.006505012512207031
    },
    {
      "config_ids": [
        13
      ],
      "costs": [
        -148.34800720214844
      ],
      "trial": 13,
      "walltime": 1.7527894973754883
    },
    {
      "config_ids": [
        15
      ],
      "costs": [
        -152.87908935546875
      ],
      "trial": 15,
      "walltime": 1.789682149887085
    },
    {
      "config_ids": [
        19
      ],
      "costs": [
        -153.77130126953125
      ],
      "trial": 19,
      "walltime": 1.8696012496948242
    },
    {
      "config_ids": [
        21
      ],
      "costs": [
        -155.37107849121094
      ],
      "trial": 21,
      "walltime": 2.916748046875
    },
    {
      "config_ids": [
        23
      ],
      "costs": [
        -165.03297424316406
      ],
      "trial": 23,
      "walltime": 2.9451920986175537
    },
    {
      "config_ids": [
        25
      ],
      "costs": [
        -220.53672790527344
      ],
      "trial": 25,
      "walltime": 2.9780032634735107
    },
    {
      "config_ids": [
        26
      ],
      "costs": [
        -236.2425537109375
      ],
      "trial": 26,
      "walltime": 2.9963650703430176
    },
    {
      "config_ids": [
        47
      ],
      "costs": [
        -240.0914764404297
      ],
      "trial": 47,
      "walltime": 6.684378623962402
    },
    {
      "config_ids": [
        49
      ],
      "costs": [
        -271.1885070800781
      ],
      "trial": 49,
      "walltime": 6.733861446380615
    }
  ],
  "state": {
    "queue": [
      [
        50,
        1
      ]
    ]
  }
}